extrapolation/__init__.py
extrapolation/esum.py
extrapolation/utils.py
extrapolation-2.1.1.dist-info/LICENSE
extrapolation-2.1.1.dist-info/METADATA
extrapolation-2.1.1.dist-info/WHEEL
extrapolation-2.1.1.dist-info/top_level.txt
extrapolation-2.1.1.dist-info/RECORD
