Metadata-Version: 2.1
Name: extrapolation
Version: 2.1.1
Summary: Extrapolation methods to real series
Home-page: https://github.com/wellington36/extrapolation_methods
Author: Wellington Silva
Author-email: <wellington.71319@gmail.com>
License: MIT
Keywords: python,series,extrapolation,numerical-analysis
License-File: LICENSE
Requires-Dist: mpmath
